query_flow/__init__.py
query_flow/parsers/__init__.py
query_flow/parsers/athena_parser.py
query_flow/parsers/db_parser.py
query_flow/parsers/postgres_parser.py
query_flow/profiler.py
query_flow/utils/__init__.py
query_flow/utils/coloring_utils.py
query_flow/utils/misc.py
query_flow/vizualizers/__init__.py
query_flow/vizualizers/query_vizualizer.py
query_flow-0.2.0.dist-info/LICENSE
query_flow-0.2.0.dist-info/WHEEL
query_flow-0.2.0.dist-info/METADATA
query_flow-0.2.0.dist-info/RECORD
